justsimplestdb/JustSimplestDB.py
justsimplestdb/__init__.py
justsimplestdb/owntypes.py
justsimplestdb-1.1.1.dist-info/METADATA
justsimplestdb-1.1.1.dist-info/WHEEL
justsimplestdb-1.1.1.dist-info/top_level.txt
justsimplestdb-1.1.1.dist-info/RECORD
